{
  "SPECIAL" : [
    {
      "name": "Strength",
      "value": "8",
      "icon": "img/ICONS/SPECIAL/S.png",
      "desc": "How much power do you weild? Just how strong are you?!"
    },
    {
      "name": "Perception",
      "value": "7",
      "icon": "img/ICONS/SPECIAL/P.png",
      "desc": "Your scouting instincts makes you more aware of your surroundings"
    },
    {
      "name": "Endurance",
      "value": "10",
      "icon": "img/ICONS/SPECIAL/E.png",
      "desc": "'You're a wall' -Red Man"
    },
    {
      "name": "Charisma",
      "value": "6",
      "icon": "img/ICONS/SPECIAL/C.png",
      "desc": "Normally, your charisma is calculated by confidence, and social standards"
    },
  {
      "name": "Intelligence",
      "value": "8",
      "icon": "img/ICONS/SPECIAL/I.png",
      "desc": "Well, how clever can you be?"
    },
    {
      "name": "Perception",
      "value": "7",
      "icon": "img/ICONS/SPECIAL/A.png",
      "desc": "How quick are your freflexes? Do you even?"
    },
    {
      "name": "Luck",
      "value": "7",
      "icon": "img/ICONS/SPECIAL/L.png",
      "desc": "On a scale of 1-10, how much of a lucky bugger are you?"
    }
  ]
  
}